LICENSE
README.md
setup.py
expl_perf_drop/KLIEP.py
expl_perf_drop/SHAPExplainer.py
expl_perf_drop/__init__.py
expl_perf_drop/experiments.py
expl_perf_drop/explain.py
expl_perf_drop/explain_janzing.py
expl_perf_drop/explainers.py
expl_perf_drop/launchers.py
expl_perf_drop/metrics.py
expl_perf_drop/models.py
expl_perf_drop/shapley.py
expl_perf_drop/sweep.py
expl_perf_drop/train_model.py
expl_perf_drop/utils.py
expl_perf_drop.egg-info/PKG-INFO
expl_perf_drop.egg-info/SOURCES.txt
expl_perf_drop.egg-info/dependency_links.txt
expl_perf_drop.egg-info/requires.txt
expl_perf_drop.egg-info/top_level.txt
expl_perf_drop/data/__init__.py
expl_perf_drop/data/camelyon.py
expl_perf_drop/data/celebA.py
expl_perf_drop/data/cmnist.py
expl_perf_drop/data/eicu.py
expl_perf_drop/data/synthetic.py