Metadata-Version: 2.1
Name: expl-perf-drop
Version: 0.5
Summary: Attributing performance drops to distribution shifts
Home-page: https://github.com/MLforHealth/expl_perf_drop
Author: Haoran Zhang
Author-email: haoranz@mit.edu
License: BSD
Platform: UNKNOWN
Requires-Python: >=3.7
License-File: LICENSE
